fastapi_querysets/__init__.py
fastapi_querysets/exceptions.py
fastapi_querysets/mixins/__init__.py
fastapi_querysets/mixins/filters.py
fastapi_querysets/mixins/ordering.py
fastapi_querysets/mixins/pagination.py
fastapi_querysets/queryset.py
fastapi_querysets-0.1.3.dist-info/LICENSE
fastapi_querysets-0.1.3.dist-info/METADATA
fastapi_querysets-0.1.3.dist-info/WHEEL
fastapi_querysets-0.1.3.dist-info/RECORD
