Metadata-Version: 2.1
Name: fastapi-querysets
Version: 0.1.3
Summary: 
Home-page: https://github.com/Nikakto/fastapi-querysets
License: MIT
Keywords: fastapi,filters,filtering,pagination,order,ordering,queryset,Tortoise,orm,database,db
Author: Nikakto
Author-email: black-z@bk.ru
Requires-Python: >=3.8,<4.0
Classifier: License :: OSI Approved :: MIT License
Classifier: Programming Language :: Python :: 3
Classifier: Programming Language :: Python :: 3.8
Classifier: Programming Language :: Python :: 3.9
Classifier: Programming Language :: Python :: 3.10
Classifier: Programming Language :: Python :: 3.11
Requires-Dist: fastapi (>=0.78)
Requires-Dist: fastapi-depends-ext (>=0.2.2)
Requires-Dist: tortoise-orm (>=0.18.1)
Project-URL: Documentation, https://fastapi-querysets.readthedocs.io
Project-URL: Repository, https://github.com/Nikakto/fastapi-querysets
